{
  "project_info": {
    "project_number": "48976215331",
    "project_id": "appvieccanlam-507ba",
    "storage_bucket": "appvieccanlam-507ba.firebasestorage.app"
  },
  "client": [
    {
      "client_info": {
        "mobilesdk_app_id": "1:48976215331:android:9525d931e9c46e04442096",
        "android_client_info": {
          "package_name": "com.trung.appvieccanlam"
        }
      },
      "oauth_client": [],
      "api_key": [
        {
          "current_key": "AIzaSyCXPDOvzmaTJo1YrSCPKnTtQkXsFGRLYl8"
        }
      ],
      "services": {
        "appinvite_service": {
          "other_platform_oauth_client": []
        }
      }
    }
  ],
  "configuration_version": "1"
}